tks_essentials-0.1.32.dist-info/licenses/LICENSE
tksessentials/__init__.py
tksessentials/asset_formatter.py
tksessentials/constants.py
tksessentials/database.py
tksessentials/global_logger.py
tksessentials/security.py
tksessentials/utils.py
tksessentials/validators.py
tks_essentials-0.1.32.dist-info/METADATA
tks_essentials-0.1.32.dist-info/WHEEL
tks_essentials-0.1.32.dist-info/top_level.txt
tks_essentials-0.1.32.dist-info/RECORD
