Metadata-Version: 2.4
Name: tks-essentials
Version: 0.1.32
Summary: Essentials for our TKS projects.
Author-email: Brayan <brayan@sparkandhale.com>
Project-URL: Homepage, https://github.com/The-Kara-System/tks-essentials
Keywords: finance,trading,models
Classifier: License :: OSI Approved :: MIT License
Classifier: Programming Language :: Python
Classifier: Programming Language :: Python :: 3
Classifier: Programming Language :: Python :: 3.12
Requires-Python: >=3.12.9
License-File: LICENSE
Requires-Dist: confluent-kafka>=2.4.0
Requires-Dist: aiokafka>=0.10.0
Requires-Dist: kafka_python>=2.0.2
Requires-Dist: cryptography>=42.0.5
Requires-Dist: email-validator>=2.1.1
Requires-Dist: httpx>=0.27.0
Requires-Dist: pyyaml>=6.0.1
Requires-Dist: pydantic>=2.7
Requires-Dist: tomli; python_version < "3.12"
Provides-Extra: dev
Requires-Dist: black; extra == "dev"
Requires-Dist: bumpver; extra == "dev"
Requires-Dist: isort; extra == "dev"
Requires-Dist: pip-tools; extra == "dev"
Requires-Dist: pytest; extra == "dev"
Requires-Dist: pytest-asyncio; extra == "dev"
Dynamic: license-file
